reaction_system-0.1.4.dist-info/METADATA
reaction_system-0.1.4.dist-info/WHEEL
reaction_system/__init__.py
reaction_system/__init__.pyi
reaction_system/py.typed
reaction_system/reaction_system.cp38-win_amd64.pyd
reaction_system-0.1.4.dist-info/RECORD
