Metadata-Version: 2.1
Name: reaction_system
Version: 0.1.4
Classifier: Programming Language :: Rust
Classifier: Programming Language :: Python :: Implementation :: CPython
Classifier: Programming Language :: Python :: Implementation :: PyPy
Summary: A package for handling Reaction Systems, and RsFunctions with minimization capabilities
Requires-Python: >=3.8
